{
  "availability-zones:account=060795936197:region=ap-south-1": [
    "ap-south-1a",
    "ap-south-1b",
    "ap-south-1c"
  ],
  "ssm:account=060795936197:parameterName=VpcId:region=ap-south-1": "vpc-07e1e64a4c48da089",
  "ssm:account=060795936197:parameterName=PrivateSubnet-0:region=ap-south-1": "subnet-05ec4e75201346c0c",
  "ssm:account=060795936197:parameterName=PrivateSubnet-1:region=ap-south-1": "subnet-08600682e40a8186c",
  "ssm:account=060795936197:parameterName=PublicSubnet-0:region=ap-south-1": "subnet-020ac88bf8cea340f",
  "ssm:account=060795936197:parameterName=PublicSubnet-1:region=ap-south-1": "subnet-0fb3c96a04a9ef5aa",
  "vpc-provider:account=060795936197:filter.vpc-id=vpc-07e1e64a4c48da089:region=ap-south-1:returnAsymmetricSubnets=true": {
    "vpcId": "vpc-07e1e64a4c48da089",
    "vpcCidrBlock": "10.0.0.0/16",
    "ownerAccountId": "060795936197",
    "availabilityZones": [],
    "subnetGroups": [
      {
        "name": "public-subnet",
        "type": "Public",
        "subnets": [
          {
            "subnetId": "subnet-020ac88bf8cea340f",
            "cidr": "10.0.0.0/24",
            "availabilityZone": "ap-south-1a",
            "routeTableId": "rtb-0f182a9ed38f1081b"
          },
          {
            "subnetId": "subnet-0fb3c96a04a9ef5aa",
            "cidr": "10.0.1.0/24",
            "availabilityZone": "ap-south-1b",
            "routeTableId": "rtb-0ae87f1f54275c2cd"
          }
        ]
      },
      {
        "name": "private-subnet",
        "type": "Private",
        "subnets": [
          {
            "subnetId": "subnet-05ec4e75201346c0c",
            "cidr": "10.0.2.0/24",
            "availabilityZone": "ap-south-1a",
            "routeTableId": "rtb-063419e05dd9ccacb"
          },
          {
            "subnetId": "subnet-08600682e40a8186c",
            "cidr": "10.0.3.0/24",
            "availabilityZone": "ap-south-1b",
            "routeTableId": "rtb-06aec82a348592ddb"
          }
        ]
      }
    ]
  },
  "ssm:account=060795936197:parameterName=ExpenseTrackerServicesNLB:region=ap-south-1": "Expens-Datab-d0vsNqTWNTWz-1a08ab86dd4cabb1.elb.ap-south-1.amazonaws.com"
}
